LICENSE
MANIFEST.in
README.rst
setup.cfg
setup.py
mdstat/__init__.py
mdstat/device.py
mdstat/device_bitmap.py
mdstat/device_header.py
mdstat/device_resync.py
mdstat/device_status.py
mdstat/disk.py
mdstat/utils.py
mdstat.egg-info/PKG-INFO
mdstat.egg-info/SOURCES.txt
mdstat.egg-info/dependency_links.txt
mdstat.egg-info/top_level.txt
tools/mdjson