Metadata-Version: 1.1
Name: mdstat
Version: 1.0.3
Summary: mdstat parser
Home-page: https://github.com/truveris/py-mdstat/
Author: Truveris Inc.
Author-email: dev@truveris.com
License: MIT License
Keywords: linux,mdstat,mdadm,mdjson,raid
Platform: UNKNOWN
Classifier: Development Status :: 5 - Production/Stable
Classifier: License :: OSI Approved :: MIT License
Classifier: Operating System :: POSIX :: Linux
Classifier: Programming Language :: Python :: 2.7
Classifier: Programming Language :: Python :: 3.3
Classifier: Programming Language :: Python :: 3.4
